epss_client/__init__.py
epss_client/cache_backends.py
epss_client/cache_config.py
epss_client/cache_interface.py
epss_client/cache_manager.py
epss_client/cli.py
epss_client/client.py
epss_client/py.typed
epss_client/types.py
epss_client-2.0.0.dist-info/licenses/LICENSE
epss_client-2.0.0.dist-info/METADATA
epss_client-2.0.0.dist-info/WHEEL
epss_client-2.0.0.dist-info/entry_points.txt
epss_client-2.0.0.dist-info/top_level.txt
epss_client-2.0.0.dist-info/RECORD
