Metadata-Version: 2.4
Name: epss-client
Version: 2.0.0
Summary: Typed Python client and CLI for FIRST EPSS (Exploit Prediction Scoring System) API
Author-email: Roshan Kumar <roshaen09@gmail.com>
License: MIT
Project-URL: Homepage, https://github.com/youhaveme9/epss-client
Project-URL: Repository, https://github.com/youhaveme9/epss-client
Project-URL: Issues, https://github.com/youhaveme9/epss-client/issues
Project-URL: Documentation, https://api.first.org/epss
Keywords: EPSS,FIRST,CVE,security,vulnerabilities,api,client
Classifier: Development Status :: 3 - Alpha
Classifier: Intended Audience :: Developers
Classifier: Intended Audience :: Information Technology
Classifier: License :: OSI Approved :: MIT License
Classifier: Programming Language :: Python
Classifier: Programming Language :: Python :: 3
Classifier: Programming Language :: Python :: 3 :: Only
Classifier: Programming Language :: Python :: 3.8
Classifier: Programming Language :: Python :: 3.9
Classifier: Programming Language :: Python :: 3.10
Classifier: Programming Language :: Python :: 3.11
Classifier: Programming Language :: Python :: 3.12
Classifier: Topic :: Security
Classifier: Topic :: Software Development :: Libraries :: Python Modules
Classifier: Typing :: Typed
Requires-Python: >=3.8
License-File: LICENSE
Requires-Dist: requests<3.0.0,>=2.28.0
Provides-Extra: test
Requires-Dist: pytest>=7.0; extra == "test"
Provides-Extra: dev
Requires-Dist: pytest>=7.0; extra == "dev"
Requires-Dist: ruff>=0.1.0; extra == "dev"
Requires-Dist: black>=23.0.0; extra == "dev"
Requires-Dist: isort>=5.12.0; extra == "dev"
Requires-Dist: pre-commit>=3.0.0; extra == "dev"
Provides-Extra: cache-redis
Requires-Dist: redis>=4.0.0; extra == "cache-redis"
Requires-Dist: hiredis>=2.0.0; extra == "cache-redis"
Provides-Extra: cache-db
Requires-Dist: sqlalchemy>=2.0.0; extra == "cache-db"
Requires-Dist: alembic>=1.8.0; extra == "cache-db"
Provides-Extra: cache-full
Requires-Dist: redis>=4.0.0; extra == "cache-full"
Requires-Dist: hiredis>=2.0.0; extra == "cache-full"
Requires-Dist: sqlalchemy>=2.0.0; extra == "cache-full"
Requires-Dist: alembic>=1.8.0; extra == "cache-full"
Requires-Dist: pyyaml>=6.0; extra == "cache-full"
Provides-Extra: config
Requires-Dist: pyyaml>=6.0; extra == "config"
Requires-Dist: toml>=0.10.0; extra == "config"
Dynamic: license-file
